cucmapi/__init__.py
cucmapi/axl.py
cucmapi/ccs.py
cucmapi/cdr.py
cucmapi/generate_axl.py
cucmapi/log.py
cucmapi/pfm.py
cucmapi/ris.py
cucmapi/schema/10.0/AXLAPI.wsdl
cucmapi/schema/10.0/AXLEnums.xsd
cucmapi/schema/10.0/AXLSoap.xsd
cucmapi/schema/10.5/AXLAPI.wsdl
cucmapi/schema/10.5/AXLEnums.xsd
cucmapi/schema/10.5/AXLSoap.xsd
cucmapi/schema/11.0/AXLAPI.wsdl
cucmapi/schema/11.0/AXLEnums.xsd
cucmapi/schema/11.0/AXLSoap.xsd
cucmapi/schema/11.5/AXLAPI.wsdl
cucmapi/schema/11.5/AXLEnums.xsd
cucmapi/schema/11.5/AXLSoap.xsd
cucmapi/schema/12.0/AXLAPI.wsdl
cucmapi/schema/12.0/AXLEnums.xsd
cucmapi/schema/12.0/AXLSoap.xsd
cucmapi/schema/12.5/AXLAPI.wsdl
cucmapi/schema/12.5/AXLEnums.xsd
cucmapi/schema/12.5/AXLSoap.xsd
cucmapi/schema/8.5/AXLAPI.wsdl
cucmapi/schema/8.5/AXLEnums.xsd
cucmapi/schema/8.5/AXLSoap.xsd
cucmapi/schema/current/AXLAPI.wsdl
cucmapi/schema/current/AXLEnums.xsd
cucmapi/schema/current/AXLSoap.xsd
cucmapi-0.0.2.dist-info/LICENSE
cucmapi-0.0.2.dist-info/METADATA
cucmapi-0.0.2.dist-info/WHEEL
cucmapi-0.0.2.dist-info/top_level.txt
cucmapi-0.0.2.dist-info/RECORD
