Metadata-Version: 2.1
Name: cucmapi
Version: 0.0.2
Summary: Python SDK for Cisco CUCM SOAP APIs
Home-page: https://github.com/awetomate/cucmapi
Author: John Frauchiger
Author-email: john.frauchiger@pm.me
Keywords: cisco,cucm,uc,collaboration,callmanager,axl,ris,soap
Classifier: Development Status :: 3 - Alpha
Classifier: Intended Audience :: Developers
Classifier: Intended Audience :: System Administrators
Classifier: Programming Language :: Python :: 3
Classifier: License :: OSI Approved :: MIT License
Classifier: Operating System :: OS Independent
Requires-Python: <4,>=3.7
License-File: LICENSE
Requires-Dist: requests
Requires-Dist: zeep
